zensols/install/__init__.py
zensols/install/download.py
zensols/install/installer.py
zensols/install/resource.py
zensols_install-1.4.0.dist-info/METADATA
zensols_install-1.4.0.dist-info/WHEEL
zensols_install-1.4.0.dist-info/licenses/LICENSE.md
zensols_install-1.4.0.dist-info/RECORD
