Metadata-Version: 2.3
Name: zensols_install
Version: 1.4.0
Summary: Simple light API to download and install (optionally compressed) files.
Project-URL: Homepage, https://github.com/plandes/install
Project-URL: Documentation, https://plandes.github.io/install
Project-URL: Repository, https://github.com/plandes/install.git
Project-URL: Issues, https://github.com/plandes/install/issues
Project-URL: Changelog, https://github.com/plandes/install/blob/master/CHANGELOG.md
Author-email: Paul Landes <landes@mailc.net>
License: MIT
Keywords: compression,resources,utility
Requires-Python: <3.15,>=3.11
Requires-Dist: patool<1.13,>=1.12
Requires-Dist: tqdm
Requires-Dist: zensols-util~=1.16.2
